hipp/__about__.py
hipp/__init__.py
hipp/image.py
hipp/intrinsics.py
hipp/math.py
hipp/tools.py
hipp/aerial/__init__.py
hipp/aerial/core.py
hipp/aerial/fiducials.py
hipp/aerial/quality_control.py
hipp/dataquery/__init__.py
hipp/dataquery/nagap.py
hipp/dataquery/utils.py
hipp/kh9pc/__init__.py
hipp/kh9pc/batch.py
hipp/kh9pc/collimation_lines.py
hipp/kh9pc/core.py
hipp/kh9pc/image_mosaic.py
hipp/kh9pc/quality_control.py
hipp-0.2.0.dist-info/METADATA
hipp-0.2.0.dist-info/WHEEL
hipp-0.2.0.dist-info/licenses/LICENSE
hipp-0.2.0.dist-info/RECORD
