Metadata-Version: 2.4
Name: hipp
Version: 0.2.0
Summary: Historical Image Pre-Processing
Project-URL: Documentation, https://github.com/godinlu/hipp#readme
Project-URL: Issues, https://github.com/godinlu/hipp/issues
Project-URL: Source, https://github.com/godinlu/hipp
Author-email: godinlu <godin.luc2002@gmail.com>
License-Expression: Apache-2.0
License-File: LICENSE
Classifier: Development Status :: 4 - Beta
Classifier: Programming Language :: Python
Classifier: Programming Language :: Python :: 3.8
Classifier: Programming Language :: Python :: 3.9
Classifier: Programming Language :: Python :: 3.10
Classifier: Programming Language :: Python :: 3.11
Classifier: Programming Language :: Python :: 3.12
Classifier: Programming Language :: Python :: Implementation :: CPython
Classifier: Programming Language :: Python :: Implementation :: PyPy
Requires-Python: >=3.8
Requires-Dist: matplotlib
Requires-Dist: numpy
Requires-Dist: opencv-python
Requires-Dist: pandas
Requires-Dist: rasterio
Requires-Dist: requests
Requires-Dist: scikit-image
Requires-Dist: scikit-learn
Requires-Dist: tqdm
